jupyter_social/__init__.py
jupyter_social/_version.py
jupyter_social/handlers.py
jupyter_social/tests/__init__.py
jupyter_social/tests/test_handlers.py
jupyter_social-0.0.3.data/data/etc/jupyter/jupyter_notebook_config.d/jupyter_social.json
jupyter_social-0.0.3.data/data/etc/jupyter/jupyter_server_config.d/jupyter_social.json
jupyter_social-0.0.3.data/data/share/jupyter/labextensions/@datalayer/jupyter-social/build_log.json
jupyter_social-0.0.3.data/data/share/jupyter/labextensions/@datalayer/jupyter-social/package.json
jupyter_social-0.0.3.data/data/share/jupyter/labextensions/@datalayer/jupyter-social/schemas/@datalayer/jupyter-social/package.json.orig
jupyter_social-0.0.3.data/data/share/jupyter/labextensions/@datalayer/jupyter-social/schemas/@datalayer/jupyter-social/plugin.json
jupyter_social-0.0.3.data/data/share/jupyter/labextensions/@datalayer/jupyter-social/static/icons_lib_index_js.c5d37a70b766b1117a70.js
jupyter_social-0.0.3.data/data/share/jupyter/labextensions/@datalayer/jupyter-social/static/icons_lib_index_js.c5d37a70b766b1117a70.js.map
jupyter_social-0.0.3.data/data/share/jupyter/labextensions/@datalayer/jupyter-social/static/lib_index_js.f185057cf7196678fb3e.js
jupyter_social-0.0.3.data/data/share/jupyter/labextensions/@datalayer/jupyter-social/static/lib_index_js.f185057cf7196678fb3e.js.map
jupyter_social-0.0.3.data/data/share/jupyter/labextensions/@datalayer/jupyter-social/static/node_modules_object-assign_index_js.a5ce5a6986752868ecf0.js
jupyter_social-0.0.3.data/data/share/jupyter/labextensions/@datalayer/jupyter-social/static/node_modules_object-assign_index_js.a5ce5a6986752868ecf0.js.map
jupyter_social-0.0.3.data/data/share/jupyter/labextensions/@datalayer/jupyter-social/static/remoteEntry.7c3a7e40f0f73c1111fd.js
jupyter_social-0.0.3.data/data/share/jupyter/labextensions/@datalayer/jupyter-social/static/remoteEntry.7c3a7e40f0f73c1111fd.js.map
jupyter_social-0.0.3.data/data/share/jupyter/labextensions/@datalayer/jupyter-social/static/style.js
jupyter_social-0.0.3.dist-info/METADATA
jupyter_social-0.0.3.dist-info/WHEEL
jupyter_social-0.0.3.dist-info/licenses/LICENSE
jupyter_social-0.0.3.dist-info/RECORD
